pybungie/BungieAPI.py
pybungie/OAuth2.py
pybungie/__init__.py
pybungie/destiny_enums.py
pybungie/config/pybungie.ini
pybungie-0.6.3.dist-info/METADATA
pybungie-0.6.3.dist-info/WHEEL
pybungie-0.6.3.dist-info/top_level.txt
pybungie-0.6.3.dist-info/RECORD
