Metadata-Version: 2.1
Name: pybungie
Version: 0.6.3
Summary: For interacting with the Bungie.net API
Home-page: https://github.com/Hayden-J-C/pybungie.git
Author: Hayden Cole
Author-email: cole.haydenj@gmail.com
License: UNKNOWN
Platform: UNKNOWN
Classifier: Programming Language :: Python :: 3
Classifier: License :: OSI Approved :: MIT License
Classifier: Operating System :: OS Independent
Requires-Python: >=3.6
Requires-Dist: requests
Requires-Dist: pyOpenSSL
Requires-Dist: python-dotenv
